[{"Date":"2020-11-06T00:00:00.000","New_Cases_Predicted":154.0,"New_Deaths_Predicted":50.0},{"Date":"2020-11-07T00:00:00.000","New_Cases_Predicted":160.0,"New_Deaths_Predicted":95.0},{"Date":"2020-11-08T00:00:00.000","New_Cases_Predicted":94.0,"New_Deaths_Predicted":50.0},{"Date":"2020-11-09T00:00:00.000","New_Cases_Predicted":183.0,"New_Deaths_Predicted":50.0},{"Date":"2020-11-10T00:00:00.000","New_Cases_Predicted":195.0,"New_Deaths_Predicted":50.0},{"Date":"2020-11-11T00:00:00.000","New_Cases_Predicted":152.0,"New_Deaths_Predicted":50.0},{"Date":"2020-11-12T00:00:00.000","New_Cases_Predicted":83.0,"New_Deaths_Predicted":95.0},{"Date":"2020-11-13T00:00:00.000","New_Cases_Predicted":106.0,"New_Deaths_Predicted":50.0},{"Date":"2020-11-14T00:00:00.000","New_Cases_Predicted":142.0,"New_Deaths_Predicted":50.0},{"Date":"2020-11-15T00:00:00.000","New_Cases_Predicted":60.0,"New_Deaths_Predicted":95.0}]